LICENSE
MANIFEST.in
README.rst
setup.cfg
setup.py
versioneer.py
src/striemann/__init__.py
src/striemann/_deprecation.py
src/striemann/_version.py
src/striemann/metrics.py
src/striemann.egg-info/PKG-INFO
src/striemann.egg-info/SOURCES.txt
src/striemann.egg-info/dependency_links.txt
src/striemann.egg-info/requires.txt
src/striemann.egg-info/top_level.txt
src/striemann.egg-info/zip-safe
src/striemann/test/__init__.py
src/striemann/test/expectsmatcher.py
src/striemann/test/fakes.py
src/striemann/tests/__init__.py
src/striemann/tests/test_striemann.py
src/striemann/tests/test_test.py