Metadata-Version: 2.1
Name: striemann
Version: 0.7.10
Summary: Send metrics to the Riemann monitoring system
Home-page: https://github.com/madedotcom/striemann
Author: Bob Gregory
License: MIT
Platform: any
Classifier: Development Status :: 4 - Beta
Classifier: Intended Audience :: Developers
Classifier: License :: OSI Approved :: MIT License
Classifier: Operating System :: POSIX
Classifier: Programming Language :: Python :: 3
License-File: LICENSE
